cfdilib/__init__.py
cfdilib/cfdicli.py
cfdilib/cfdilib.py
cfdilib/cfdv32.py
cfdilib/cfdv33.py
cfdilib/signatory.py
cfdilib/tools.py
cfdilib/templates/CatalogosParaEsqContE.xsd
cfdilib/templates/catCFDI.xsd
cfdilib/templates/catComExt.xsd
cfdilib/templates/catNomina.xsd
cfdilib/templates/catPagos.xsd
cfdilib/templates/cfdi13balance.xml
cfdilib/templates/cfdi13balance.xsd
cfdilib/templates/cfdi13coa.xml
cfdilib/templates/cfdi13coa.xsd
cfdilib/templates/cfdi13moves.xml
cfdilib/templates/cfdi13moves.xsd
cfdilib/templates/cfdv32.xml
cfdilib/templates/cfdv32.xsd
cfdilib/templates/cfdv33.xml
cfdilib/templates/cfdv33.xsd
cfdilib/templates/externaltrade11.xsd
cfdilib/templates/implocal.xsd
cfdilib/templates/payment10.xml
cfdilib/templates/payment10.xsd
cfdilib/templates/payroll12.xml
cfdilib/templates/payroll12.xsd
cfdilib/templates/tdcfdi.xsd
cfdilib-0.7.3.dist-info/DESCRIPTION.rst
cfdilib-0.7.3.dist-info/METADATA
cfdilib-0.7.3.dist-info/RECORD
cfdilib-0.7.3.dist-info/WHEEL
cfdilib-0.7.3.dist-info/entry_points.txt
cfdilib-0.7.3.dist-info/metadata.json
cfdilib-0.7.3.dist-info/top_level.txt
