Metadata-Version: 2.0
Name: cfdilib
Version: 0.7.3
Summary: Library to manage xml CDFI from python and sign with several pacs.
Home-page: https://github.com/vauxoo/cfdilib
Author: Vauxoo OpenSource Specialists.
Author-email: mexico@vauxoo.com
License: ISCL
Keywords: cfdilib
Platform: UNKNOWN
Classifier: Development Status :: 2 - Pre-Alpha
Classifier: Intended Audience :: Developers
Classifier: License :: OSI Approved :: ISC License (ISCL)
Classifier: Natural Language :: English
Classifier: Programming Language :: Python :: 2
Classifier: Programming Language :: Python :: 2.6
Classifier: Programming Language :: Python :: 2.7
Classifier: Programming Language :: Python :: 3
Classifier: Programming Language :: Python :: 3.3
Classifier: Programming Language :: Python :: 3.4
Classifier: Programming Language :: Python :: 3.5
Requires-Dist: backports.functools-lru-cache
Requires-Dist: boto3
Requires-Dist: click
Requires-Dist: jinja2
